simple_mecab/__init__.py
simple_mecab/_version.py
simple_mecab/exceptions.py
simple_mecab/mecab_wrapper.py
simple_mecab/morpheme.py
simple_mecab-1.2.1.dist-info/LICENSE
simple_mecab-1.2.1.dist-info/METADATA
simple_mecab-1.2.1.dist-info/WHEEL
simple_mecab-1.2.1.dist-info/top_level.txt
simple_mecab-1.2.1.dist-info/RECORD
