Metadata-Version: 2.1
Name: simple-mecab
Version: 1.2.1
Summary: Use MeCab with simple code.
Author-email: Keisuke Magara <Keisuke-Magara.dev@outlook.com>
License: MIT License
Project-URL: repository, https://github.com/Keisuke-Magara/simple-mecab
Keywords: mecab,NLP,morphological-analysis
Classifier: Programming Language :: Python :: 3.10
Classifier: Intended Audience :: Science/Research
Classifier: License :: OSI Approved :: MIT License
Classifier: Natural Language :: Japanese
Requires-Python: >=3.7
License-File: LICENSE
Requires-Dist: mecab (>=0.996)
